bytecompute/__init__.py
bytecompute-0.1.43.dist-info/METADATA
bytecompute-0.1.43.dist-info/WHEEL
bytecompute-0.1.43.dist-info/top_level.txt
bytecompute-0.1.43.dist-info/RECORD
