Metadata-Version: 2.4
Name: bytecompute
Version: 0.1.43
Summary: bytecompute
Requires-Python: >=3.10
